{
  "updated_at": "2026-03-11T13:40:00.000Z",
  "geo": "all",
  "type": "all",
  "count": 1,
  "bonuses": [
    {
      "id": "astrocrash-1",
      "name": "AstroCrashGame",
      "slug": "astrocrashgame",
      "brand": "AstroCrash",
      "geo": ["in", "global"],
      "logo": "https://luckybetvip.com/wp-content/uploads/2024/03/astrocrash-logo.jpg",
      "rating": 9.9,
      "features": ["Instant Telegram Play", "Provably Fair", "Huge Multipliers"],
      "bonuses": [
        {
          "type": "Welcome Bonus",
          "amount": "Up to 500% Match + 100 Free Flights",
          "code": "1x_4393603"
        }
      ],
      "highlights": [
        "Play directly in Telegram Messenger",
        "Instant Crypto & UPI Withdrawals",
        "Exclusive VIP Cashback"
      ],
      "link": "https://t.me/AstroCrashGame_bot",
      "tags": ["Crash Game", "Telegram Casino", "Crypto"],
      "isPlatform": true
    }
  ]
}
